nfiparcel/__init__.py
tests/__init__.py
tests/common.py
tests/test_cli.py
nfiparcel-0.0.0.dist-info/LICENSE
nfiparcel-0.0.0.dist-info/METADATA
nfiparcel-0.0.0.dist-info/WHEEL
nfiparcel-0.0.0.dist-info/entry_points.txt
nfiparcel-0.0.0.dist-info/top_level.txt
nfiparcel-0.0.0.dist-info/RECORD
