Metadata-Version: 2.1
Name: nfiparcel
Version: 0.0.0
Summary: Python package for parcel analysis and rating.
Home-page: https://github.com/NFI-Industries/nfiparcel
Author: Chris Pryer
Author-email: chris.pryer@nfiindustries.com
License: PUBLIC
Platform: UNKNOWN
Requires-Dist: atomicwrites (==1.4.0)
Requires-Dist: attrs (==19.3.0)
Requires-Dist: colorama (==0.4.3)
Requires-Dist: more-itertools (==8.3.0)
Requires-Dist: numpy (==1.18.4)
Requires-Dist: packaging (==20.4)
Requires-Dist: pandas (==1.0.3)
Requires-Dist: pluggy (==0.13.1)
Requires-Dist: py (==1.8.1)
Requires-Dist: pyparsing (==2.4.7)
Requires-Dist: pytest (==5.4.2)
Requires-Dist: python-dateutil (==2.8.1)
Requires-Dist: pytz (==2020.1)
Requires-Dist: six (==1.15.0)
Requires-Dist: wcwidth (==0.1.9)
